norm_findings/__init__.py
norm_findings/_version.py
norm_findings/api.py
norm_findings/cli.py
norm_findings/converter.py
norm_findings/server.py
norm_findings/updater.py
norm_findings/parsers/parser_test.py
norm_findings/stubs/models.py
norm_findings/stubs/utils.py
norm_findings-0.3.0.dist-info/licenses/NOTICE
norm_findings-0.3.0.dist-info/METADATA
norm_findings-0.3.0.dist-info/WHEEL
norm_findings-0.3.0.dist-info/entry_points.txt
norm_findings-0.3.0.dist-info/top_level.txt
norm_findings-0.3.0.dist-info/RECORD
