Metadata-Version: 2.4
Name: norm-findings
Version: 0.3.0
Summary: A lean CLI tool for normalizing security scanner findings based on DefectDojo parsers.
License: Apache-2.0
Requires-Python: >=3.9
License-File: NOTICE
Requires-Dist: jsonargparse[signatures]
Requires-Dist: astunparse
Requires-Dist: ujson
Requires-Dist: hyperlink
Requires-Dist: cvss
Requires-Dist: html2text
Requires-Dist: lxml
Requires-Dist: cpe
Requires-Dist: openpyxl
Requires-Dist: defusedxml
Requires-Dist: packageurl-python
Requires-Dist: vulners
Requires-Dist: netaddr
Requires-Dist: python-dateutil
Requires-Dist: requests
Requires-Dist: blackduck
Provides-Extra: server
Requires-Dist: uvicorn; extra == "server"
Requires-Dist: fastapi; extra == "server"
Provides-Extra: dev
Requires-Dist: pytest; extra == "dev"
Requires-Dist: pytest-cov; extra == "dev"
Requires-Dist: build; extra == "dev"
Requires-Dist: twine; extra == "dev"
Requires-Dist: python-semantic-release; extra == "dev"
Dynamic: license-file
